pastemyst/__init__.py
pastemyst/__version__.py
pastemyst/api/__init__.py
pastemyst/api/http.py
pastemyst/api/locks.py
pastemyst/client.py
pastemyst/constants.py
pastemyst/models/__init__.py
pastemyst/models/errors.py
pastemyst/models/language.py
pastemyst/models/paste.py
pastemyst/models/user.py
pastemyst/utils/__init__.py
pastemyst/utils/helpers.py
pastemyst-3.0.0.dist-info/LICENSE
pastemyst-3.0.0.dist-info/METADATA
pastemyst-3.0.0.dist-info/WHEEL
pastemyst-3.0.0.dist-info/RECORD
