Metadata-Version: 2.1
Name: pastemyst
Version: 3.0.0
Summary: api wrapper for paste.myst.rs
Author: munchii
Author-email: daniellmunch@gmail.com
Requires-Python: >=3.12,<4.0
Classifier: Programming Language :: Python :: 3
Classifier: Programming Language :: Python :: 3.12
Requires-Dist: httpx (>=0.26.0,<0.27.0)
Requires-Dist: trio (>=0.24.0,<0.25.0)
